{
    "name": "Rimpnint",
    "primaryType": "Fighting",
    "secondaryType": "",
    "species": "Mask Ninja",
    "height": "1.2",
    "weight": "28.0",
    "catchRate": 120,
    "baseExp": 130,
    "baseFriendship": 70,
    "hiddenAbilities": "Steadfast",
    "dexEntry": "The mask on Rimpnint’s head has fused to its body, symbolizing its mastery of stealth. It begins using precise strikes in battle.",
    "abilities": "Inner Focus, Limber",
    "stats": {
        "hp": 60,
        "atk": 85,
        "def": 60,
        "spd": 85,
        "spatk": 40,
        "spdef": 60
    },
    "evolutions": [
        {
            "nr": "076",
            "name": "Ninmin",
            "lvl": 0
        },
        {
            "nr": "077",
            "name": "Rimpnint",
            "lvl": 16
        },
        {
            "nr": "078",
            "name": "Rimpcrush",
            "lvl": 35
        }
    ],
    "moves": [
        { "lvl": 1, "name": "Mach Punch" },
        { "lvl": 1, "name": "Double Team" },
        { "lvl": 14, "name": "Low Sweep" },
        { "lvl": 18, "name": "Feint" },
        { "lvl": 22, "name": "Bulk Up" },
        { "lvl": 26, "name": "Brick Break" },
        { "lvl": 32, "name": "Focus Energy" },
        { "lvl": 36, "name": "Cross Chop" }
    ],
    "tutorMoves": [
        "Brick Break", "Low Sweep", "Cross Chop", "Bulk Up", "Double Team", "Acrobatics", "Toxic", "Substitute", "Protect", "Focus Energy"
    ]
}
